resoto_plugin_vsphere/__init__.py
resoto_plugin_vsphere/config.py
resoto_plugin_vsphere/resources.py
resoto_plugin_vsphere/vsphere_client.py
resoto_plugin_vsphere-3.9.0.dist-info/LICENSE
resoto_plugin_vsphere-3.9.0.dist-info/METADATA
resoto_plugin_vsphere-3.9.0.dist-info/WHEEL
resoto_plugin_vsphere-3.9.0.dist-info/entry_points.txt
resoto_plugin_vsphere-3.9.0.dist-info/top_level.txt
resoto_plugin_vsphere-3.9.0.dist-info/RECORD
